jarvis/__init__.py
jarvis/hello_world.py
jarvis_helloworld/__init__.py
jarvis_helloworld/hello_world.py
jarvis_helloworld-0.1.0.dist-info/METADATA
jarvis_helloworld-0.1.0.dist-info/RECORD
jarvis_helloworld-0.1.0.dist-info/WHEEL
jarvis_helloworld-0.1.0.dist-info/top_level.txt
