Metadata-Version: 2.1
Name: jarvis-helloworld
Version: 0.1.0
Summary: jarvis test project
Home-page: UNKNOWN
Author: Jarvis Wang
Author-email: 172762619@qq.com
License: MIT
Platform: UNKNOWN
